{"transcript":"demeler","exists":true,"definitions":["Séparer ce qui est emmêlé, défaire les nœuds.","Résoudre une affaire compliquée, éclaircir une situation confuse.","Distinguer, différencier des choses qui semblent confondues."],"examples":["Elle a passé des heures à démêler ses cheveux.","Il faut démêler le vrai du faux dans cette histoire.","Les enquêteurs tentent de démêler l'écheveau de l'affaire."],"lemma":"démêler","lemmaPos":"verb","synonyms":["dénouer","détricoter","éclaircir","résoudre","distinguer"],"number":"singular","pastTenses":"démêlé, a démêlé","tense":"present","source":"démêler"}