{"source":"privé","number":"singular","lemma":"priver","lemmaPos":"verb","definitions":["Qui est soustrait à la jouissance, à la possession de quelque chose.","Qui est privé de quelque chose, qui en est dépourvu.","Qui est personnel, particulier, non public."],"examples":["Il est privé de ses droits.","Elle se sent privée de liberté.","C'est un espace privé."],"synonyms":["dépourvu","soustrait","personnel","particulier"],"transcript":"pʁive","gender":"masculine","tense":"past","pastTenses":"il a privé, il avait privé"}