{"transcript":"tʁa.dɥi","exists":true,"definitions":["Action de transposer un texte ou des propos d'une langue à une autre.","Action de faire comprendre, d'exprimer une idée ou un sentiment.","Action de réduire en un état, de transformer."],"examples":["Je traduis un livre.","Tu traduis bien tes pensées.","Cela se traduis par des actes."],"lemma":"traduire","lemmaPos":"verb","synonyms":["interpréter","transcrire","exprimer","rendre"],"number":"singular","pastTenses":"j'ai traduit, tu as traduit, il/elle a traduit, nous avons traduit, vous avez traduit, ils/elles ont traduit","tense":"present","source":"traduis"}