{"transcript":"altɛʁnɑ̃s","exists":true,"definitions":["Succession régulière de choses ou de phénomènes.","Système de formation qui combine des périodes d'enseignement théorique et des périodes de travail en entreprise.","Changement de majorité politique au pouvoir."],"examples":["L'alternance des saisons est un phénomène naturel.","Il a choisi l'alternance pour sa formation.","Le pays a connu une alternance politique pacifique."],"lemma":"alternance","lemmaPos":"noun","synonyms":["succession","roulement","relais"],"number":"singular","pluralForm":"les alternances","gender":"feminine","source":"alternance"}