{"transcript":"ʁɑ̃.ty","exists":true,"definitions":["Deuxième personne du singulier du verbe « se rendre » au présent de l'indicatif, forme interrogative.","Deuxième personne du singulier du verbe « rendre » au présent de l'indicatif, forme interrogative."],"examples":["Rends-tu les livres à la bibliothèque ?","Rends-tu compte de la situation ?","Rends-tu visite à tes parents ce week-end ?"],"lemma":"rendre","lemmaPos":"verb","synonyms":["livrer","restituer","devenir","céder"],"number":"singular","pastTenses":"tu as rendu, tu t'es rendu","tense":"present","source":"rends-tu"}