{"transcript":"kʁe.ma.jɛʁ","exists":true,"definitions":["Tige de métal munie de crans permettant de suspendre une marmite au-dessus du feu.","Dispositif mécanique constitué d'une barre dentée s'engrenant avec une roue.","Fête organisée pour célébrer l'installation dans un nouveau logement."],"examples":["Pendre la crémaillère.","Un système de direction à crémaillère.","La marmite pend à la crémaillère."],"lemma":"crémaillère","lemmaPos":"noun","synonyms":["crémaillon","engrenage"],"number":"singular","pluralForm":"les crémaillères","gender":"feminine","source":"crémaillère"}