{"transcript":"lak.sism","exists":true,"definitions":["Tendance à la tolérance excessive, au manque de rigueur.","Attitude de quelqu'un qui fait preuve de trop d'indulgence, de laisser-aller."],"examples":["Le laxisme des parents peut avoir des conséquences.","Il dénonce le laxisme de la justice.","Un certain laxisme s'est installé dans l'entreprise."],"lemma":"laxisme","lemmaPos":"noun","synonyms":["indulgence","tolérance","relâchement","négligence","laisser-aller"],"number":"singular","pluralForm":"les laxismes","gender":"masculine","source":"laxisme"}