{"source":"portée","number":"singular","lemma":"porter","lemmaPos":"verb","definitions":["étendue jusqu'où porte quelque chose","capacité ou mesure de ce que l'on peut faire","action de porter une chose ou une personne","ensemble de jeunes animaux d'une même mère","ensemble des notes musicales sur une partition"],"examples":["La bombe a une grande portée.","La portée de ses actions est considérable.","Portée des chiots.","L'orchestre joue une nouvelle portée."],"synonyms":["ampleur","extension","influence","effet","allonge"],"transcript":"pɔʁ.te","gender":"feminine"}