{"transcript":"ɛkstʁɛʁ","exists":true,"definitions":["Tirer quelque chose de l'endroit où il est inséré, fixé, inclus.","Retirer une substance d'un mélange, d'un corps.","Obtenir des informations, des données à partir d'une source."],"examples":["Extraire une dent.","Extraire le jus d'un fruit.","Extraire des données d'une base."],"lemma":"extraire","lemmaPos":"verb","synonyms":["tirer","retirer","arracher","sortir"],"number":"singular","pastTenses":"j'ai extrait, tu as extrait, il/elle a extrait, nous avons extrait, vous avez extrait, ils/elles ont extrait","tense":"present","source":"extraire"}