{"transcript":"ʃuʃute","source":"chouchouter","definitions":["Traiter quelqu'un ou quelque chose avec beaucoup de soin, d'affection et d'attention, souvent de manière excessive ou indulgente.","Dorloter, gâter, cocooner."],"examples":["Elle aime chouchouter ses petits-enfants.","Il faut chouchouter cette plante fragile.","Les clients sont chouchoutés dans cet hôtel."],"lemma":"chouchouter","lemmaPos":"verb","synonyms":["dorloter","gâter","cocooner","cajoler","choyer","mignoter"],"number":"singular","gender":"other"}