{"source":"trinquons","number":"plural","lemma":"trinquer","lemmaPos":"verb","definitions":["Forme conjuguée du verbe trinquer à la première personne du pluriel de l'indicatif présent.","Forme conjuguée du verbe trinquer à la première personne du pluriel de l'impératif présent."],"examples":["Trinquons à votre santé !","Si nous trinquons, c'est pour célébrer.","Trinquons avant de partir."],"synonyms":["porter un toast","boire à la santé de","célébrer"],"transcript":"tʁɛ̃.kɔ̃","tense":"present","pastTenses":"nous avons trinqué, nous avions trinqué"}