{"transcript":"e.klɛʁ.siʁ","exists":true,"definitions":["Rendre plus clair, moins opaque.","Rendre moins dense, moins épais.","Rendre plus compréhensible, plus limpide.","Dégager, espacer des plantes trop serrées."],"examples":["Il faut éclaircir la sauce.","Le soleil a éclairci le ciel.","J'ai éclairci mes idées.","Nous allons éclaircir les rangs de salades."],"lemma":"éclaircir","lemmaPos":"verb","synonyms":["clarifier","élucider","diluer","dégager"],"number":"singular","pastTenses":"a éclairci, avait éclairci","tense":"present","source":"éclaircir"}