{"transcript":"sy.pɛʁ.vi.ze","exists":true,"definitions":["Diriger et contrôler le travail de quelqu'un ou d'un groupe.","Surveiller l'exécution d'une tâche ou d'un projet.","Assurer la bonne marche et la conformité d'une activité."],"examples":["Il doit superviser l'équipe.","Elle supervise le projet depuis le début.","Nous allons superviser les opérations."],"lemma":"superviser","lemmaPos":"verb","synonyms":["surveiller","contrôler","diriger","gérer","encadrer"],"number":"singular","pastTenses":"il a supervisé, il avait supervisé","tense":"present","source":"superviser"}