{"transcript":"ʁə.sə.ve.vu","exists":true,"definitions":["Forme interrogative de la deuxième personne du pluriel du verbe recevoir au présent de l'indicatif.","Action de prendre possession de quelque chose.","Action d'accueillir quelqu'un."],"examples":["Recevez-vous mes lettres régulièrement ?","Recevez-vous des invités ce soir ?","Recevez-vous le signal de la télévision ?"],"lemma":"recevoir","lemmaPos":"verb","synonyms":["obtenir","accueillir","percevoir"],"number":"plural","pastTenses":"vous avez reçu, vous receviez","tense":"present","source":"recevez-vous"}