{"transcript":"ɛs.te.ti.sjɛn","exists":true,"definitions":["Professionnelle spécialisée dans les soins de beauté du corps et du visage.","Personne qui pratique des soins esthétiques en institut ou à domicile."],"examples":["L'esthéticienne m'a fait un soin du visage.","Elle travaille comme esthéticienne dans un spa."],"lemma":"esthéticienne","lemmaPos":"noun","synonyms":["cosméticienne","visagiste"],"number":"singular","pluralForm":"les esthéticiennes","gender":"feminine","source":"esthéticienne"}