{"transcript":"a.lɔ̃ʒ.mɑ̃","exists":true,"definitions":["Action d'allonger ou de devenir plus long.","Accroissement de la durée d'une chose.","Augmentation de la dimension d'un corps sous l'effet d'une force."],"examples":["L'allongement des jours au printemps.","L'allongement d'un délai de paiement.","L'allongement d'un métal sous tension."],"lemma":"allongement","lemmaPos":"noun","synonyms":["l'étirement","la prolongation","l'extension","l'agrandissement"],"number":"singular","pluralForm":"les allongements","gender":"masculine","source":"l'allongement"}