{"transcript":"ɡut","exists":true,"definitions":["Percevoir la saveur de quelque chose par le sens du goût.","Prendre une petite quantité de nourriture ou de boisson pour en apprécier la saveur.","Faire l'expérience de quelque chose, en ressentir les effets."],"examples":["Il goûte le vin avant de le servir.","Elle goûte toujours les plats avant de les saler.","Le chef goûte sa sauce pour l'ajuster."],"lemma":"goûter","lemmaPos":"verb","synonyms":["savourer","déguster","tester","expérimenter"],"number":"singular","pastTenses":"a goûté, a goûté","tense":"present","source":"goûte"}