{"transcript":"me.tʁaʒ","exists":true,"definitions":["Action de mesurer en mètres.","Longueur mesurée en mètres.","Durée d'un film, d'une vidéo.","Ensemble des scènes tournées pour un film."],"examples":["Le métrage du tissu est important.","Un métrage de 120 minutes.","Le métrage brut est impressionnant.","Le métrage final a été réduit."],"lemma":"métrage","lemmaPos":"noun","synonyms":["longueur","durée","mesure"],"number":"singular","pluralForm":"les métrages","gender":"masculine","source":"métrage"}