{"transcript":"ʒwe","exists":true,"definitions":["Participe passé du verbe jouer.","Action de s'amuser, de prendre part à un jeu.","Action de représenter un rôle au théâtre ou au cinéma.","Action de manipuler un instrument de musique."],"examples":["Il a joué toute la nuit.","Elle a joué un rôle important dans la pièce.","Le musicien a joué un morceau magnifique.","L'enfant a joué avec ses amis."],"lemma":"jouer","lemmaPos":"verb","synonyms":["s'amuser","interpréter","exécuter","gambader"],"number":"singular","pastTenses":"il a joué, il est joué","tense":"past","source":"joué"}