{"transcript":"ɛ̃.pli.ke","exists":true,"definitions":["Qui sont mêlés à une affaire, une situation.","Qui sont engagés émotionnellement ou personnellement.","Qui sont sous-entendus, sous-jacents."],"examples":["Les témoins étaient impliqués dans le scandale.","Ils se sont sentis très impliqués dans le projet.","Les risques impliqués sont considérables."],"lemma":"impliquer","lemmaPos":"verb","synonyms":["mêlés","engagés","concernés"],"number":"plural","tense":"past","pastTenses":"ont impliqué, ont été impliqués","gender":"masculine","source":"impliqués"}