{"transcript":"ad.mɛ.tɑ̃","exists":true,"definitions":["Forme du verbe admettre au participe présent.","Qui reconnaît la vérité ou la validité de quelque chose.","Qui permet l'accès ou l'entrée."],"examples":["Admettant son erreur, il s'excusa.","La loi, admettant certaines exceptions, reste stricte.","Une porte admettant la lumière du jour."],"lemma":"admettre","lemmaPos":"verb","synonyms":["reconnaître","accepter","concéder","permettre"],"number":"singular","pastTenses":"il a admis, il avait admis","tense":"present","source":"admettant"}