{"transcript":"sistemɑtikmɑ̃","exists":true,"definitions":["De manière systématique, en suivant un système.","Avec régularité, de façon constante et organisée.","Sans exception, à chaque fois."],"examples":["Il vérifie systématiquement toutes les données.","Elle répond systématiquement à ses courriels.","Nous appliquons systématiquement cette règle."],"lemma":"systématique","lemmaPos":"adjective","synonyms":["régulièrement","constamment","méthodiquement","invariablement"],"number":"singular","source":"systématiquement"}