{"transcript":"aplodisɔ̃","exists":true,"definitions":["Forme conjuguée du verbe applaudir à la première personne du pluriel de l'indicatif présent ou de l'impératif présent.","Exprimer notre approbation ou notre admiration par des applaudissements.","Frapper des mains en signe d'approbation."],"examples":["Nous applaudissons les artistes après leur performance.","Applaudissons tous ensemble pour le vainqueur !","Quand le rideau tombe, nous applaudissons toujours."],"lemma":"applaudir","lemmaPos":"verb","synonyms":["ovationner","acclamer","féliciter"],"number":"plural","pastTenses":"nous avons applaudi, nous applaudîmes","tense":"present","source":"applaudissons"}