{"transcript":"pi.ʁa.te","exists":true,"definitions":["Qui a été volé ou copié illégalement (logiciel, œuvre d'art, etc.).","Qui a été attaqué et compromis (système informatique, compte en ligne)."],"examples":["Le film piraté circulait sur internet.","Son compte a été piraté hier soir.","Les données piratées ont été rendues publiques."],"lemma":"pirater","lemmaPos":"verb","synonyms":["contrefaire","hacker","détourner","voler"],"number":"singular","pastTenses":"il a piraté, il avait piraté","tense":"past","source":"piraté"}