{"transcript":"ɔ.ky.pə.ʁɛ","exists":true,"definitions":["Forme du verbe « occuper » à la première personne du singulier du conditionnel présent.","Forme du verbe « occuper » à la deuxième personne du singulier du conditionnel présent."],"examples":["Si j'avais le temps, je m'occuperais de ce projet.","Tu t'occuperais de la réservation, n'est-ce pas ?"],"lemma":"occuper","lemmaPos":"verb","synonyms":["prendre en charge","gérer","s'employer à","prendre soin de"],"number":"singular","pastTenses":"j'ai occupé, tu as occupé, il a occupé, nous avons occupé, vous avez occupé, ils ont occupé","tense":"conditional","source":"occuperais"}