{"transcript":"klɑse","exists":true,"definitions":["Forme féminine singulière du participe passé du verbe classer.","Qui a été rangée ou organisée selon une catégorie.","Qui a été désignée ou reconnue officiellement (ex: monument classé)."],"examples":["La lettre a été classée par ordre alphabétique.","Cette espèce est classée comme menacée.","L'œuvre d'art a été classée trésor national."],"lemma":"classer","lemmaPos":"verb","synonyms":["ranger","trier","catégoriser","répertorier"],"number":"singular","pastTenses":"classa, a classé","tense":"past","gender":"feminine","source":"classée"}