{"transcript":"mɛ̃.tjɛn","exists":true,"definitions":["Ils ou elles gardent quelque chose dans un certain état ou position.","Ils ou elles soutiennent une idée, une opinion ou une situation.","Ils ou elles continuent à faire exister quelque chose."],"examples":["Les piliers maintiennent le toit.","Ils maintiennent leur position malgré l'opposition.","Les lois maintiennent l'ordre social."],"lemma":"maintenir","lemmaPos":"verb","synonyms":["gardent","soutiennent","conservent","préservent"],"number":"plural","pastTenses":"ont maintenu, avaient maintenu","tense":"present","source":"maintiennent"}