{"transcript":"vwa","exists":true,"definitions":["Percevoir par la vue.","Comprendre, concevoir.","Rencontrer quelqu'un.","Être témoin de quelque chose."],"examples":["Je vois un oiseau dans le ciel.","Tu vois ce que je veux dire ?","Il voit ses amis tous les jours.","On voit souvent ce genre de situation."],"lemma":"voir","lemmaPos":"verb","synonyms":["apercevoir","regarder","discerner","comprendre"],"number":"singular","pastTenses":"j'ai vu, tu as vu, il a vu, nous avons vu, vous avez vu, ils ont vu","tense":"present","source":"vois"}