{"transcript":"pʁɑ̃dʁa","exists":true,"definitions":["Deuxième personne du singulier du futur simple du verbe prendre.","Action de saisir, d'emporter, d'acquérir ou de choisir à l'avenir."],"examples":["Tu prendras le train de 8h.","Quand tu prendras ta décision, fais-le moi savoir.","Tu prendras un dessert après le repas."],"lemma":"prendre","lemmaPos":"verb","synonyms":["saisiras","choisiras","emporteras","acquerras"],"number":"singular","pastTenses":"tu pris, tu as pris","tense":"future","source":"prendras"}