{"transcript":"a.ʁi.vɛ","exists":true,"definitions":["Forme conjuguée du verbe « arriver » à l'imparfait de l'indicatif, troisième personne du singulier.","Venait à un lieu ou un moment donné.","Survenait, se produisait."],"examples":["Il arrivait toujours en retard.","Quand elle arrivait, tout le monde souriait.","Le train arrivait à quai."],"lemma":"arriver","lemmaPos":"verb","synonyms":["parvenait","venait","survenait","advenait"],"number":"singular","pastTenses":"il est arrivé, il est arrivé","tense":"past","source":"arrivait"}