{"transcript":"a.ʁɛ.tɛ","exists":true,"definitions":["Forme du verbe « arrêter » à l'imparfait de l'indicatif, première personne du singulier.","Forme du verbe « arrêter » à l'imparfait de l'indicatif, deuxième personne du singulier."],"examples":["J'arrêtais de fumer l'année dernière.","Tu arrêtais le bus à chaque arrêt."],"lemma":"arrêter","lemmaPos":"verb","synonyms":["cessais","stoppais","interrompais"],"number":"singular","pastTenses":"j'ai arrêté, tu as arrêté","tense":"past","source":"arrêtais"}