{"transcript":"du.ʃe","exists":true,"definitions":["Laver quelqu'un ou se laver sous une douche.","Arroser abondamment quelque chose avec de l'eau.","Décourager, décevoir quelqu'un."],"examples":["Je vais me doucher avant de sortir.","Il a douché les espoirs de son adversaire.","Le jardinier douche les plantes avec un tuyau."],"lemma":"doucher","lemmaPos":"verb","synonyms":["laver","arroser","décourager"],"number":"singular","pastTenses":"j'ai douché, j'avais douché","tense":"present","source":"doucher"}