{"transcript":"imaʒe","exists":true,"definitions":["Représenter par des images.","Illustrer un texte avec des images.","Se représenter mentalement quelque chose."],"examples":["Il aime imager ses récits.","L'artiste a imagé la scène avec brio.","Elle s'efforce d'imager son avenir."],"lemma":"imager","lemmaPos":"verb","synonyms":["illustrer","représenter","dépeindre"],"number":"singular","pastTenses":"j'ai imagé, tu as imagé, il a imagé, nous avons imagé, vous avez imagé, ils ont imagé","tense":"present","source":"imager"}