{"transcript":"ʁə.bɛ.le","exists":true,"definitions":["Se révolter, s'insurger contre une autorité, une loi.","Manifester son opposition, sa désobéissance."],"examples":["Les citoyens ont commencé à se rebeller.","Il est temps de se rebeller contre l'injustice.","Elle se rebelle souvent contre les règles établies."],"lemma":"se rebeller","lemmaPos":"verb","synonyms":["révolter","insurger","mutiner","désobéir"],"number":"singular","pastTenses":"s'est rebellé, s'est rebellée, se sont rebellés, se sont rebellées, s'était rebellé, s'était rebellée, s'étaient rebellés, s'étaient rebellées","tense":"present","source":"rebeller"}