{"transcript":"pu.se","exists":true,"definitions":["Action de pousser, d'exercer une pression pour déplacer quelque chose ou quelqu'un.","Inciter, encourager quelqu'un à faire quelque chose.","Faire croître, développer (en parlant de plantes, de cheveux, etc.).","Émettre un son, un cri (familier)."],"examples":["Poussez la porte pour entrer.","Poussez-le à étudier davantage.","Les plantes poussez vite avec ce soleil.","Poussez un cri de joie."],"lemma":"pousser","lemmaPos":"verb","synonyms":["pousser","presser","inciter","encourager","développer"],"number":"plural","pastTenses":"vous avez poussé, vous poussiez","tense":"present","source":"poussez"}