{"transcript":"su.la.ʒe","exists":true,"definitions":["Diminuer une douleur physique ou morale.","Apporter un réconfort, une aide.","Décharger d'un fardeau, d'une tâche."],"examples":["Ce médicament va soulager votre douleur.","Il a été soulagé d'apprendre la bonne nouvelle.","Nous devons soulager les personnes dans le besoin.","Elle a soulagé son sac à dos en le posant."],"lemma":"soulager","lemmaPos":"verb","synonyms":["apaiser","calmer","détendre","alléger","décharger"],"number":"singular","pastTenses":"soulagé, a soulagé","tense":"present","source":"soulager"}