{"transcript":"de.ʁɑ̃.ʒe","exists":true,"definitions":["Mettre en désordre, troubler l'ordre de quelque chose.","Causer du souci, de l'ennui à quelqu'un.","Interrompre quelqu'un dans son activité."],"examples":["Ne dérangez pas les papiers sur mon bureau.","Vous dérangez tout le monde avec votre bruit.","Désolé de vous déranger pendant votre travail."],"lemma":"déranger","lemmaPos":"verb","synonyms":["perturber","troubler","importuner","gêner"],"number":"plural","pastTenses":"vous avez dérangé, vous dérangeâtes","tense":"present","source":"dérangez"}