{"source":"pelle","number":"singular","lemma":"peller","lemmaPos":"verb","definitions":["Action de pelleter, de creuser avec une pelle.","Forme conjuguée du verbe « peller » à la première ou troisième personne du singulier de l'indicatif présent.","Forme conjuguée du verbe « peller » à la première ou troisième personne du singulier du subjonctif présent.","Forme conjuguée du verbe « peller » à la deuxième personne du singulier de l'impératif présent."],"examples":["Il pelle la terre pour planter les fleurs.","Que je pelle le sable rapidement.","Pelle le charbon dans la chaudière."],"synonyms":["creuser","bêcher","déblayer"],"transcript":"pɛl","tense":"present","pastTenses":"il a pellé, il avait pellé"}