{"transcript":"ʁafʁeʃiʁ","exists":true,"definitions":["Rendre plus frais, moins chaud.","Redonner de la vigueur, de l'énergie.","Rendre plus récent, actualiser.","Boire ou manger quelque chose de frais pour se désaltérer."],"examples":["Rafraîchir une boisson.","Rafraîchir la mémoire de quelqu'un.","Rafraîchir une page web.","Se rafraîchir avec une limonade."],"lemma":"rafraîchir","lemmaPos":"verb","synonyms":["réfrigérer","détendre","actualiser","désaltérer"],"number":"singular","pastTenses":"il a rafraîchi, il rafraîchit","tense":"present","source":"rafraîchir"}