{"transcript":"ɡʁuj","exists":true,"definitions":["Se déplacer en grand nombre, en parlant d'insectes, de petits animaux ou de personnes.","Abonder, être rempli de quelque chose, souvent de manière désordonnée."],"examples":["Les fourmis grouillent sur le sucre.","La foule grouillent dans les rues du marché.","Des idées grouillent dans son esprit."],"lemma":"grouiller","lemmaPos":"verb","synonyms":["pulluler","foisonner","fourmiller"],"number":"plural","tense":"present","pastTenses":"ils ont grouillé, ils grouillèrent","source":"grouillent"}