{"transcript":"ɛ̃vɛsti","exists":true,"definitions":["Participe passé du verbe investir.","Qui a été placé dans quelque chose (argent, temps, effort).","Qui a été pourvu d'une fonction, d'un pouvoir.","Qui est fortement impliqué émotionnellement ou personnellement."],"examples":["Il a investi toutes ses économies dans ce projet.","Elle s'est senti investi d'une mission.","Les fonds ont été investi judicieusement.","Il est très investi dans son travail."],"lemma":"investir","lemmaPos":"verb","synonyms":["placer","doter","impliquer","consacrer"],"number":"singular","pastTenses":"il a investi, il est investi","tense":"past","gender":"masculine","source":"investi"}