{"transcript":"ɛ.dɛ","exists":true,"definitions":["Forme de l'imparfait du verbe « aider ».","Apporter son aide, son soutien à quelqu'un ou quelque chose.","Contribuer à la réalisation de quelque chose."],"examples":["Il aidait toujours ses amis.","La pluie aidait les cultures à pousser.","Elle aidait sa mère à faire la cuisine."],"lemma":"aider","lemmaPos":"verb","synonyms":["soutenir","assister","secourir","contribuer"],"number":"singular","pastTenses":"il a aidé, il avait aidé","tense":"past","source":"aidait"}