{"transcript":"fɔʁme","exists":true,"definitions":["Donner une forme à quelque chose.","Constituer, créer, établir.","Instruire, éduquer, entraîner quelqu'un à une profession ou une activité.","Développer, acquérir (une habitude, une opinion)."],"examples":["Il faut former la pâte avant de la cuire.","Les étudiants vont former un groupe de travail.","L'université a pour mission de former les futurs cadres.","Il est important de former de bonnes habitudes dès l'enfance."],"lemma":"former","lemmaPos":"verb","synonyms":["façonner","constituer","éduquer","créer","instruire"],"number":"singular","pastTenses":"formé, a formé","tense":"present","source":"former"}