{"transcript":"pɔʃ","exists":true,"definitions":["Petit sac de tissu ou de matière souple, cousu à un vêtement, un sac, etc., et servant à ranger de petits objets.","Cavité naturelle ou artificielle.","Quantité de liquide ou de matière contenue dans une poche."],"examples":["Mettre les clés dans sa poche.","Une poche de kangourou.","Une poche de sang."],"lemma":"poche","lemmaPos":"noun","synonyms":["sac","sacoche","blouse"],"number":"singular","pluralForm":"les poches","gender":"feminine","source":"poche"}