{"transcript":"pɑ̃ʃe","exists":true,"definitions":["Incliner, faire incliner quelque chose ou quelqu'un.","Se courber, s'incliner dans une direction.","Avoir une préférence, une propension pour quelque chose."],"examples":["Il faut pencher la tête pour passer sous la poutre.","La tour de Pise penche.","Mon cœur penche vers la justice."],"lemma":"pencher","lemmaPos":"verb","synonyms":["incliner","courber","ployer","préférer"],"number":"singular","pastTenses":"il a penché, il est penché","tense":"present","source":"pencher"}