{"transcript":"ɑ̃tɑ̃dɛ","exists":true,"definitions":["Forme de l'imparfait de l'indicatif du verbe entendre à la troisième personne du pluriel.","Avoir la faculté d'ouïr, de percevoir des sons.","Comprendre, saisir le sens de quelque chose.","Vouloir dire, signifier.","S'accorder, être d'accord avec quelqu'un."],"examples":["Ils entendaient les oiseaux chanter chaque matin.","Elles entendaient bien ce qu'il leur expliquait.","Ils entendaient que la situation change.","Elles s'entendaient à merveille."],"lemma":"entendre","lemmaPos":"verb","synonyms":["ouïr","comprendre","saisir","percevoir","écouter"],"number":"plural","pastTenses":"ils entendaient, ils ont entendu","tense":"past","source":"entendaient"}