{"transcript":"ʁəkɔ̃dɥiʁ","exists":true,"definitions":["Raccompagner quelqu'un à l'endroit d'où il est venu ou à un autre lieu.","Prolonger un contrat, un mandat, un bail.","Renvoyer quelqu'un, l'expulser (sens figuré ou propre)."],"examples":["Je vais le reconduire à la gare.","Le contrat a été reconduit pour un an.","Ils l'ont reconduit à la frontière."],"lemma":"reconduire","lemmaPos":"verb","synonyms":["raccompagner","prolonger","expulser"],"number":"singular","pastTenses":"j'ai reconduit, tu as reconduit, il/elle a reconduit, nous avons reconduit, vous avez reconduit, ils/elles ont reconduit","tense":"present","source":"reconduire"}