{"transcript":"pʁi z‿ɑ̃.n‿e.to","exists":true,"definitions":["Serré, bloqué entre deux forces ou deux éléments.","Dans une situation difficile, sans issue, où l'on est contraint par des forces opposées."],"examples":["La voiture était prise en étau entre les deux camions.","Il se sentait pris en étau entre son travail et sa famille.","L'entreprise est prise en étau entre la baisse des ventes et l'augmentation des coûts."],"lemma":"pris en étau","lemmaPos":"adjective","synonyms":["coincé","bloqué","serré","contraint","piégé"],"number":"singular","gender":"masculine","source":"pris en étau"}