{"transcript":"i.ɡɔʁ mɔ.ni","exists":true,"definitions":["Igor Monni est un boxeur professionnel français.","Il est connu pour sa carrière dans la boxe anglaise."],"examples":["Igor Monni a remporté plusieurs titres nationaux.","Le style de combat d'Igor Monni est très apprécié.","Les fans ont acclamé Igor Monni lors de son dernier match."],"lemma":"Igor Monni","lemmaPos":"proper noun","synonyms":["Le boxeur Monni","Monni"],"number":"singular","pluralForm":"les Igor Monni","gender":"masculine","source":"Igor Monni"}