{"transcript":"pʁetɑ̃dɛ","exists":true,"definitions":["Affirmait quelque chose comme vrai, souvent sans preuve.","Aspirait à un titre, une position ou une qualité.","Se donnait l'apparence de quelque chose."],"examples":["Il prétendait connaître la vérité.","Elle prétendait au trône.","Le vieil homme prétendait être malade."],"lemma":"prétendre","lemmaPos":"verb","synonyms":["affirmer","revendiquer","aspirer"],"number":"singular","pastTenses":"il a prétendu, il avait prétendu","tense":"past","source":"prétendait"}