{"transcript":"kɔ̃tinɥɛ","exists":true,"definitions":["Forme du verbe « continuer » à la troisième personne du singulier de l'imparfait de l'indicatif.","Poursuivait une action, un état ou un processus.","Perdurait dans le temps."],"examples":["Il continuait son travail malgré la fatigue.","La pluie continuait de tomber sans relâche.","Elle continuait à croire en ses rêves."],"lemma":"continuer","lemmaPos":"verb","synonyms":["poursuivait","prolongeait","perdurait","persistait"],"number":"singular","pastTenses":"il a continué, il avait continué","tense":"past","source":"continuait"}