{"transcript":"pʁɔfanasjɔ̃","source":"profanation","definitions":["Action de profaner, de traiter sans respect une chose sacrée.","Action de dégrader ou de souiller un lieu, un objet ou un symbole considéré comme sacré ou vénérable."],"examples":["La profanation de l'église a choqué la communauté.","Il a été accusé de profanation pour avoir vandalisé le monument."],"lemma":"profanation","lemmaPos":"noun","synonyms":["sacrilège","souillure","violation","désacralisation"],"number":"singular","gender":"feminine"}