{"transcript":"kalm(ə)twa","exists":true,"definitions":["Forme impérative du verbe « se calmer » à la deuxième personne du singulier, utilisée pour demander à quelqu'un de retrouver son calme, de se tranquilliser."],"examples":["Calme-toi, tout va bien se passer.","Quand tu es stressé, respire profondément et calme-toi.","Il faut que tu te calmes-toi avant de parler."],"lemma":"se calmer","lemmaPos":"verb","synonyms":["détends-toi","tranquillise-toi","apaise-toi"],"number":"singular","pastTenses":"tu t'es calmé, tu t'es calmée","tense":"present","source":"calme-toi"}