{"transcript":"pʁɔstitɥe","exists":true,"definitions":["Offrir des services sexuels en échange d'argent.","Dégrader, avilir quelque chose ou quelqu'un en le détournant de sa fonction ou de sa dignité."],"examples":["Elle a décidé de se prostituer pour survivre.","Il ne faut pas prostituer son talent pour la gloire.","L'artiste a refusé de prostituer son art."],"lemma":"prostituer","lemmaPos":"verb","synonyms":["vendre","avilir","dégrader","corrompre"],"number":"singular","pastTenses":"prostitua, a prostitué","tense":"present","source":"prostituer"}