{"transcript":"ʃɑ̃bʁə də bɔn","exists":true,"definitions":["Petite pièce, souvent située sous les toits, destinée à loger le personnel de maison.","Pièce exiguë, généralement au dernier étage d'un immeuble ancien, souvent louée à des étudiants ou des jeunes travailleurs."],"examples":["Elle a transformé sa chambre de bonne en atelier d'artiste.","Beaucoup d'étudiants cherchent une chambre de bonne à Paris.","La chambre de bonne était minuscule mais fonctionnelle."],"lemma":"chambre de bonne","lemmaPos":"noun","synonyms":["mansarde","galetas"],"number":"singular","pluralForm":"les chambres de bonne","gender":"feminine","source":"chambre de bonne"}