{"transcript":"o.ɡy.ʁe","exists":true,"definitions":["Prévoir, laisser présager, faire pressentir (quelque chose, souvent un événement futur).","Tirer des augures, prédire l'avenir par l'interprétation de signes."],"examples":["Cela n'augure rien de bon.","Les signes auguraient une bonne récolte.","Il augure de l'avenir avec optimisme."],"lemma":"augurer","lemmaPos":"verb","synonyms":["prédire","présager","pressentir","pronostiquer"],"number":"singular","tense":"present","pastTenses":"il a auguré, il augura","source":"augurer"}