{"source":"cycadées","number":"plural","lemma":"cycadée","lemmaPos":"noun","definitions":["Famille de plantes gymnospermes, souvent considérées comme des fossiles vivants.","Plantes arborescentes ou arbustives des régions tropicales et subtropicales, ressemblant à des palmiers ou des fougères."],"examples":["Les cycadées sont des plantes très anciennes.","On trouve des cycadées dans les jardins botaniques.","La reproduction des cycadées est particulière."],"synonyms":["cycas","palmier-sago"],"transcript":"sika.de","gender":"feminine"}