{"transcript":"sə.me","exists":true,"definitions":["Participe passé masculin pluriel du verbe semer.","Action de répandre des graines sur une surface pour qu'elles germent.","Action de disperser, de répandre quelque chose."],"examples":["Les champs semés promettent une bonne récolte.","Des indices semés ici et là ont aidé à résoudre l'énigme.","Les doutes semés par ses paroles ont grandi."],"lemma":"semer","lemmaPos":"verb","synonyms":["planter","répandre","disperser","éparpiller"],"number":"plural","pastTenses":"il a semé, il avait semé","tense":"past","gender":"masculine","source":"semés"}