{"transcript":"de.fi.e","exists":true,"definitions":["Provoquer quelqu'un en duel, au combat.","Mettre au défi, provoquer quelqu'un à faire quelque chose.","Braver, affronter avec audace.","Inspirer de la méfiance, se méfier de."],"examples":["Il a défié son adversaire.","Je te défie de sauter.","Défier le danger.","Il se défie de tout le monde."],"lemma":"défier","lemmaPos":"verb","synonyms":["provoquer","braver","affronter","contester"],"number":"singular","pastTenses":"il a défié, il avait défié","tense":"present","source":"défier"}