{"transcript":"fɛʁ muʃ","exists":true,"definitions":["Atteindre son but avec précision.","Réussir parfaitement une action, un coup.","Faire mouche signifie atteindre la cible, réussir son coup, faire une impression forte et juste."],"examples":["Sa remarque a fait mouche.","Le tireur a fait mouche à chaque fois.","Son argument a fait mouche auprès de l'auditoire."],"lemma":"faire mouche","lemmaPos":"verb","synonyms":["atteindre la cible","réussir","toucher au but"],"number":"singular","tense":"present","pastTenses":"a fait mouche, a fait mouche","source":"faire mouche"}