{"source":"piqûre","number":"singular","lemma":"piqûre","lemmaPos":"noun","definitions":["Action de piquer, de percer avec une pointe.","Marque laissée par une piqûre.","Injection sous-cutanée ou intramusculaire d'un médicament.","Sensation de douleur causée par une piqûre d'insecte ou d'animal."],"examples":["La piqûre d'une aiguille.","Une piqûre de moustique.","Faire une piqûre de rappel.","La piqûre d'une abeille."],"synonyms":["injection","morsure","piqure"],"transcript":"pi.kyʁ","gender":"feminine","pluralForm":"les piqûres"}