{"transcript":"pu.ʁɛ","exists":true,"definitions":["Conditionnel présent du verbe pouvoir à la première ou deuxième personne du singulier.","Exprime une possibilité, une capacité, une permission ou une suggestion au conditionnel."],"examples":["Je pourrais t'aider si tu veux.","Tu pourrais essayer une autre méthode.","Il pourrais venir demain.","Nous pourrions partir plus tôt."],"lemma":"pouvoir","lemmaPos":"verb","synonyms":["savoir","être capable de","avoir la faculté de"],"number":"singular","pastTenses":"j'ai pu, tu as pu, il a pu, nous avons pu, vous avez pu, ils ont pu","tense":"conditional","source":"pourrais"}