{"transcript":"mɑ̃ʒe","exists":true,"definitions":["Participe passé masculin pluriel du verbe manger.","Qui ont été consommés comme nourriture."],"examples":["Les fruits ont été mangés par les enfants.","Ces gâteaux sont délicieux, ils ont tous été mangés."],"lemma":"manger","lemmaPos":"verb","synonyms":["avalés","consommés","dégustés"],"number":"plural","pastTenses":"j'ai mangé, tu as mangé, il/elle a mangé, nous avons mangé, vous avez mangé, ils/elles ont mangé","tense":"past","gender":"masculine","source":"mangés"}