{"transcript":"ʁə.ku.ʁiʁ","exists":true,"definitions":["Avoir recours à quelque chose ou quelqu'un pour obtenir de l'aide, un conseil, un soutien.","Utiliser un moyen, une méthode pour atteindre un but.","Faire appel à une instance supérieure (justice, autorité)."],"examples":["Il a dû recourir à la force.","Nous devons recourir à des mesures extrêmes.","Elle a décidé de recourir en appel."],"lemma":"recourir","lemmaPos":"verb","synonyms":["faire appel","avoir recours","utiliser","employer"],"number":"singular","pastTenses":"il a recouru, il est recouru","tense":"present","source":"recourir"}