{"transcript":"ʁə.mɛtʁ ɑ̃ koz","exists":true,"definitions":["Questionner la validité ou la légitimité de quelque chose.","Remettre en question, contester, douter de.","Changer d'avis sur une décision ou une situation antérieure."],"examples":["Il faut remettre en cause cette décision.","Ne remets pas en cause son intégrité.","La crise a remis en cause nos certitudes."],"lemma":"remettre en cause","lemmaPos":"verb","synonyms":["contester","questionner","douter","critiquer"],"number":"singular","pastTenses":"a remis en cause, avait remis en cause","tense":"present","source":"remettre en cause"}