{"source":"tangage","number":"singular","lemma":"tangage","lemmaPos":"noun","definitions":["Mouvement de rotation d'un navire ou d'un aéronef autour de son axe transversal, provoquant une alternance de l'avant vers le haut et vers le bas.","Action de tanguer."],"examples":["Le tangage du bateau rendait la traversée difficile.","Les passagers ont ressenti un fort tangage pendant la tempête.","Le système de stabilisation réduit le tangage de l'avion."],"synonyms":["pitch","roulis"],"transcript":"tɑ̃.ɡaʒ","gender":"masculine"}