{"transcript":"ɑ̃tɑ̃dʁ","exists":true,"definitions":["Percevoir par l'ouïe, saisir un son.","Comprendre, saisir le sens de quelque chose.","Avoir l'intention de faire quelque chose.","Donner audience à quelqu'un, écouter ce qu'il a à dire."],"examples":["J'entends la musique.","Il entend ce que tu dis.","Nous entendons partir demain.","Le juge va entendre le témoin."],"lemma":"entendre","lemmaPos":"verb","synonyms":["écouter","ouïr","comprendre","saisir"],"number":"singular","pastTenses":"j'ai entendu, tu as entendu, il a entendu, nous avons entendu, vous avez entendu, ils ont entendu","tense":"present","source":"entendre"}