{"transcript":"ɡaʁde vu","exists":true,"definitions":["Forme conjuguée du verbe « se garder » à la deuxième personne du pluriel de l'impératif présent ou du présent de l'indicatif.","Prenez garde, soyez vigilant.","Évitez de faire quelque chose."],"examples":["Gardez-vous de tout danger.","Gardez-vous d'oublier votre promesse.","Gardez-vous bien au chaud."],"lemma":"se garder","lemmaPos":"verb","synonyms":["méfiez-vous","prenez garde","évitez"],"number":"plural","pastTenses":"vous vous êtes gardé, vous vous êtes gardés","tense":"present","source":"gardez-vous"}