{"transcript":"ʁə.pɛ̃dʁ","exists":true,"definitions":["Peindre de nouveau quelque chose.","Appliquer une nouvelle couche de peinture sur une surface déjà peinte."],"examples":["Il faut repeindre le mur.","Nous allons repeindre la cuisine ce week-end.","Elle a décidé de repeindre ses volets."],"lemma":"repeindre","lemmaPos":"verb","synonyms":["repeinturer","rénover","rafraîchir"],"number":"singular","pastTenses":"j'ai repeint, tu as repeint, il a repeint, nous avons repeint, vous avez repeint, ils ont repeint","tense":"present","source":"repeindre"}