{"transcript":"pʁɔtɛʒ","exists":true,"definitions":["Deuxième personne du singulier du présent de l'indicatif du verbe protéger.","Deuxième personne du singulier du subjonctif présent du verbe protéger."],"examples":["Tu protèges l'environnement.","Il faut que tu protèges tes données.","Si tu protèges ton cœur, tu évites la douleur."],"lemma":"protéger","lemmaPos":"verb","synonyms":["défends","sauves","gardes","préserve"],"number":"singular","pastTenses":"tu as protégé, tu protégeais","tense":"present","source":"protèges"}