{"transcript":"ɑ̃bale","exists":true,"definitions":["Mis dans un emballage","Enthousiasmés, excités","S'être emportés, s'être énervés"],"examples":["Les cadeaux étaient emballés avec soin.","Ils étaient emballés par la nouvelle.","Les chevaux se sont emballés."],"lemma":"emballer","lemmaPos":"verb","synonyms":["paquetés","enthousiasmés","excités","emportés"],"number":"plural","pastTenses":"emballé, a emballé, ont emballé, a été emballé, ont été emballés","tense":"past","gender":"masculine","source":"emballés"}