{"transcript":"ʁə.tuʁ.nə.ʁɔ̃","exists":true,"definitions":["Action de revenir à un lieu, un état antérieur.","Action de faire demi-tour, de changer de direction.","Action de rendre quelque chose à son propriétaire ou à son lieu d'origine."],"examples":["Nous retournerons à Paris l'année prochaine.","Ils retournerons les livres à la bibliothèque.","Vous retournerons la situation à votre avantage."],"lemma":"retourner","lemmaPos":"verb","synonyms":["revenir","rejoindre","rendre"],"number":"plural","pastTenses":"nous sommes retournés, nous avons retourné","tense":"future","source":"retournerons"}