{"transcript":"sɔ̃ də la paʁɔl","source":"son de la parole","definitions":["Unité sonore fondamentale du langage humain, produite par l'appareil phonatoire et perçue par l'oreille.","Élément acoustique distinctif qui contribue à la signification des mots et des phrases.","Phénomène physique et physiologique de la production et de la réception des sons utilisés dans la communication verbale."],"examples":["L'étude du son de la parole est la phonétique.","Chaque langue a ses propres sons de la parole.","Les enfants apprennent à distinguer les sons de la parole."],"lemma":"son de la parole","lemmaPos":"noun","synonyms":["phonème","son linguistique","son vocal"],"number":"singular","gender":"masculine"}