{"transcript":"ʁə.pe.ʁe","exists":true,"definitions":["Identifier l'emplacement de quelque chose ou de quelqu'un.","Distinguer, reconnaître quelque chose ou quelqu'un parmi d'autres.","Marquer un point de repère."],"examples":["Il a repéré l'entrée du tunnel.","Elle a repéré ses amis dans la foule.","Nous devons repérer les erreurs dans le texte."],"lemma":"repérer","lemmaPos":"verb","synonyms":["localiser","identifier","détecter","discerner"],"number":"singular","pastTenses":"il a repéré, il est repéré","tense":"present","source":"repérer"}