{"transcript":"deʃifʁe","exists":true,"definitions":["Comprendre un texte ou un code difficile à lire.","Interpréter une écriture ou un langage secret.","Démêler ce qui est confus ou obscur."],"examples":["Il a déchiffré le message secret.","Elle a déchiffré la partition de musique.","Nous avons déchiffré l'énigme."],"lemma":"déchiffrer","lemmaPos":"verb","synonyms":["décoder","décrypter","interpréter","comprendre"],"number":"singular","pastTenses":"j'ai déchiffré, tu as déchiffré, il/elle a déchiffré, nous avons déchiffré, vous avez déchiffré, ils/elles ont déchiffré","tense":"past","source":"déchiffré"}