{"transcript":"paʁle-vu","exists":true,"definitions":["Forme interrogative ou emphatique de la deuxième personne du pluriel ou de la forme de politesse du verbe parler.","Utilisé pour demander si quelqu'un a la capacité ou l'habitude de parler une langue."],"examples":["Parlez-vous français ?","Parlez-vous plus fort, s'il vous plaît.","Parlez-vous souvent de vos voyages ?"],"lemma":"parler","lemmaPos":"verb","synonyms":["discuter","converser","s'exprimer"],"number":"plural","pastTenses":"vous avez parlé, vous parliez","tense":"present","source":"parlez-vous"}