{"transcript":"swe.tə.ʁɛ","exists":true,"definitions":["Forme conditionnelle du verbe souhaiter, exprimant un désir ou une volonté.","Indique une requête polie ou un souhait hypothétique."],"examples":["Je souhaiterais partir en vacances.","Nous souhaiterais visiter Paris.","Il souhaiterais que tu viennes."],"lemma":"souhaiter","lemmaPos":"verb","synonyms":["désirerais","aimerais","voudrais"],"number":"singular","pastTenses":"j'ai souhaité, j'avais souhaité","tense":"conditional","source":"souhaiterais"}