{"transcript":"l'ɛ̃ʒenjœʁ","exists":true,"definitions":["Personne qui a reçu une formation scientifique et technique de haut niveau et qui est chargée de concevoir, de réaliser, de gérer des projets dans divers domaines (industrie, bâtiment, informatique, etc.).","Titre d'une personne diplômée d'une école d'ingénieurs."],"examples":["L'ingénieur conçoit des ponts.","Elle est ingénieur en informatique.","Le projet a été mené par un ingénieur expérimenté."],"lemma":"ingénieur","lemmaPos":"noun","synonyms":["concepteur","technicien","architecte"],"number":"singular","pluralForm":"les ingénieurs","gender":"masculine","source":"l’ingénieur"}