{"transcript":"am(ə)ne le","exists":true,"definitions":["Forme impérative du verbe « amener » à la deuxième personne du pluriel, suivie du pronom objet direct « les ».","Conduire ou transporter plusieurs personnes ou choses à un endroit.","Faire venir plusieurs personnes ou choses."],"examples":["Amenez-les ici, s'il vous plaît.","Amenez-les à la réunion.","Amenez-les avec vous."],"lemma":"amener","lemmaPos":"verb","synonyms":["mener","porter","conduire","emmener"],"number":"plural","pastTenses":"vous avez amené, vous aviez amené","tense":"present","source":"amenez-les"}