{"transcript":"a.vwaʁ la.bi.tyd","exists":true,"definitions":["Être accoutumé à quelque chose","Faire quelque chose régulièrement, par habitude"],"examples":["J'ai l'habitude de me lever tôt.","Ils ont l'habitude de voyager en été.","Nous avions l'habitude de nous promener ici."],"lemma":"avoir l'habitude","lemmaPos":"verb phrase","synonyms":["être habitué","être accoutumé","avoir coutume"],"number":"singular","pastTenses":"j'ai eu l'habitude, j'avais eu l'habitude","tense":"present","source":"avoir l'habitude"}