{"transcript":"ɔkypɔ̃","exists":true,"definitions":["Forme conjuguée du verbe « occuper » à la première personne du pluriel de l'indicatif présent.","Forme conjuguée du verbe « occuper » à la première personne du pluriel de l'impératif présent."],"examples":["Nous occupons la première place.","Occupons-nous de cette tâche immédiatement.","Nous occupons nos journées à travailler."],"lemma":"occuper","lemmaPos":"verb","synonyms":["prendre","remplir","employer","habiter","saisir"],"number":"plural","pastTenses":"nous avons occupé, nous occupâmes","tense":"present","source":"occupons"}