{"exists":true,"definitions":["Convenir aux goûts ou aux préférences de quelqu'un.","Plaire à quelqu'un.","Correspondre aux attentes ou aux centres d'intérêt de quelqu'un."],"examples":["Le football n'est pas vraiment ma tasse de thé.","Ce genre de musique est tout à fait sa tasse de thé.","Les films d'horreur ne sont pas la tasse de thé de tout le monde."],"lemma":"être la tasse de thé de quelqu'un","lemmaPos":"idiom","synonyms":["convenir à quelqu'un","plaire à quelqu'un","être du goût de quelqu'un"],"number":"singular","source":"être la tasse de thé de quelqu'un","transcript":""}