{"transcript":"syʁvivʁ","exists":true,"definitions":["Continuer à vivre après un événement difficile ou la mort de quelqu'un.","Subsister, perdurer malgré les obstacles.","Vivre plus longtemps que quelqu'un d'autre."],"examples":["Il a réussi à survivre à l'accident.","L'espèce a survécu grâce à son adaptation.","Elle a survécu à son mari de dix ans."],"lemma":"survivre","lemmaPos":"verb","synonyms":["subsister","perdurer","résister","durer"],"number":"singular","pastTenses":"il a survécu, il est survécu","tense":"present","source":"survivre"}