{"transcript":"ʁap.lɛ","exists":true,"definitions":["Forme du verbe « rappeler » à la troisième personne du singulier de l'imparfait de l'indicatif.","Évoquait le souvenir de quelque chose ou de quelqu'un.","Faisait revenir à la mémoire.","Demandait à quelqu'un de revenir."],"examples":["Son parfum rappelait les lilas du jardin.","Il rappelait souvent l'importance de la patience.","La sonnerie rappelait les élèves en classe.","Elle rappelait son chien d'un simple sifflement."],"lemma":"rappeler","lemmaPos":"verb","synonyms":["évoquait","remémorait","convoquait","signalait"],"number":"singular","pastTenses":"il a rappelé, il avait rappelé","tense":"past","source":"rappelait"}