{"transcript":"ʁəsəvɛ","exists":true,"definitions":["Forme conjuguée du verbe « recevoir » à l'imparfait de l'indicatif, première ou deuxième personne du singulier.","Action de prendre possession de quelque chose qui est donné, envoyé ou transmis.","Action d'accueillir quelqu'un."],"examples":["Je recevais toujours des lettres de ma grand-mère.","Tu recevais beaucoup de cadeaux pour ton anniversaire.","Il recevais ses amis avec joie."],"lemma":"recevoir","lemmaPos":"verb","synonyms":["obtenir","accueillir","percevoir"],"number":"singular","pastTenses":"j'ai reçu, tu as reçu","tense":"past","source":"recevais"}