{"transcript":"ʁɑ̃vɛʁs","exists":true,"definitions":["Fait tomber ce qui était debout.","Change la position normale de quelque chose.","Annule une décision, un jugement.","Dépasse, surpasse."],"examples":["Il renverse la table par accident.","Le vent renverse les arbres.","La cour d'appel renverse le verdict.","Son talent renverse toutes les attentes."],"lemma":"renverser","lemmaPos":"verb","synonyms":["culbuter","chavirer","annuler","dépasser"],"number":"singular","pastTenses":"a renversé, est renversé","tense":"present","source":"renverse"}