{"transcript":"ʒu.ɛ̃","exists":true,"definitions":["Forme du verbe « jouer » à la troisième personne du pluriel de l'imparfait de l'indicatif.","Ils ou elles étaient en train de s'amuser, de pratiquer un jeu ou un sport.","Ils ou elles interprétaient un rôle dans une pièce de théâtre ou un film.","Ils ou elles utilisaient un instrument de musique."],"examples":["Les enfants jouaient dans le jardin.","Ils jouaient aux cartes toute la soirée.","Les acteurs jouaient leur rôle avec passion.","Les musiciens jouaient une mélodie entraînante."],"lemma":"jouer","lemmaPos":"verb","synonyms":["s'amuser","divertir","interpréter","exécuter"],"number":"plural","pastTenses":"ils ont joué, ils avaient joué","tense":"past","source":"jouaient"}