{"transcript":"pʁiviləʒje","exists":true,"definitions":["Accorder un privilège, un avantage particulier à quelqu'un ou à quelque chose.","Choisir de préférence, donner la priorité à quelque chose."],"examples":["Il faut privilégier les circuits courts.","Nous privilégions la qualité sur la quantité.","Les entreprises privilégient souvent l'expérience."],"lemma":"privilégier","lemmaPos":"verb","synonyms":["favoriser","préférer","avantager","choisir"],"number":"singular","pastTenses":"il a privilégié, il a privilégié","tense":"present","source":"privilégier"}