{"transcript":"ʁabese","exists":true,"definitions":["Diminuer la hauteur de quelque chose.","Déprécier, humilier quelqu'un.","Réduire l'importance, la valeur de quelque chose."],"examples":["Il a rabaissé le prix de la voiture.","Elle se sent rabaissée par ses collègues.","Ne rabaissons pas l'importance de ce détail."],"lemma":"rabaisser","lemmaPos":"verb","synonyms":["abaisser","diminuer","humilier","déprécier"],"number":"singular","pastTenses":"il a rabaissé, il est rabaissé","tense":"present","source":"rabaisser"}