{"source":"pardon","number":"singular","lemma":"pardon","lemmaPos":"interjection","definitions":["Exprime des excuses pour une faute, une gêne causée.","Utilisé pour demander à quelqu'un de répéter ce qu'il vient de dire.","Employé pour attirer l'attention de quelqu'un.","Marque la surprise ou l'incrédulité."],"examples":["Pardon, je vous ai bousculé.","Pardon, vous pouvez répéter ?","Pardon, monsieur, quelle heure est-il ?","Pardon, vous avez dit quoi ?"],"synonyms":["excusez-moi","désolé","s'il vous plaît"],"transcript":"paʁdɔ̃"}