{"transcript":"puʁi","exists":true,"definitions":["Troisième personne du singulier de l'indicatif présent du verbe pourrir.","Deuxième personne du singulier de l'impératif présent du verbe pourrir."],"examples":["Le fruit pourrit sur l'arbre.","Il pourrit la situation avec ses mensonges.","Pourrit cette pomme avant qu'elle ne contamine les autres."],"lemma":"pourrir","lemmaPos":"verb","synonyms":["décomposer","gâter","corrompre","détériorer"],"number":"singular","pastTenses":"il a pourri, il est pourri","tense":"present","source":"pourrit"}