{"transcript":"e.pu.ze","exists":true,"definitions":["Forme du participe passé masculin singulier du verbe épouser.","Forme du passé simple du verbe épouser à la première ou deuxième personne du singulier."],"examples":["Il a épousé sa femme il y a dix ans.","Elle avait épousé la cause de la justice.","J'épousai cette idée sans hésitation."],"lemma":"épouser","lemmaPos":"verb","synonyms":["marier","unir","convoler"],"number":"singular","pastTenses":"épousa, a épousé, avait épousé","tense":"past","gender":"masculine","source":"épousé"}