{"transcript":"tʁuv","exists":true,"definitions":["Deuxième personne du pluriel du présent de l'indicatif du verbe trouver.","Deuxième personne du pluriel de l'impératif présent du verbe trouver."],"examples":["Vous trouvez la solution.","Trouvez un moyen de sortir.","Que trouvez-vous intéressant dans ce livre ?"],"lemma":"trouver","lemmaPos":"verb","synonyms":["découvrir","rencontrer","estimer","inventer"],"number":"plural","pastTenses":"vous avez trouvé, vous trouviez","tense":"present","source":"trouvez"}