{"transcript":"emɑ̃sipe","exists":true,"definitions":["Libérer quelqu'un d'une autorité, d'une dépendance, d'une contrainte.","Accorder à quelqu'un la pleine jouissance de ses droits civiques.","S'affranchir d'une règle, d'une tradition, d'une influence."],"examples":["Il faut émanciper les jeunes de cette tutelle.","La loi visait à émanciper les femmes.","Elle a réussi à s'émanciper des conventions sociales."],"lemma":"émanciper","lemmaPos":"verb","synonyms":["libérer","affranchir","délivrer","autonomiser"],"number":"singular","tense":"present","pastTenses":"il a émancipé, il émancipa","source":"émanciper"}