{"transcript":"nu ʁə.ʒwɛ̃dʁ","exists":true,"definitions":["Nous rejoindre signifie l'action de nous rejoindre, de venir avec nous, de se joindre à notre groupe ou à notre activité."],"examples":["Ils ont décidé de nous rejoindre pour le dîner.","Si vous voulez nous rejoindre, nous serons au parc.","Elle nous a demandé de la rejoindre plus tard."],"lemma":"rejoindre","lemmaPos":"verb","synonyms":["nous accompagner","nous suivre","nous retrouver"],"number":"plural","pastTenses":"nous avons rejoint, nous rejoignîmes","tense":"present","source":"nous rejoindre"}