{"transcript":"dəvʁɔ̃","exists":true,"definitions":["Forme conjuguée du verbe devoir à la troisième personne du pluriel du futur simple de l'indicatif.","Avoir l'obligation de faire quelque chose.","Être dans la nécessité de faire quelque chose."],"examples":["Ils devront partir tôt demain.","Les étudiants devront rendre leur travail avant vendredi.","Nous devrons prendre une décision rapidement."],"lemma":"devoir","lemmaPos":"verb","synonyms":["falloir","être obligé","être contraint"],"number":"plural","pastTenses":"ont dû, avaient dû","tense":"future","source":"devront"}