{"transcript":"ɑ̃.bʁa.se","exists":true,"definitions":["Action de serrer quelqu'un dans ses bras en signe d'affection.","Action de joindre ses lèvres à celles de quelqu'un en signe d'amour ou d'affection.","Action d'adopter une idée, une cause, une profession."],"examples":["Elle a été embrassée par sa mère.","La proposition a été embrassée par l'assemblée.","La cause a été embrassée avec ferveur."],"lemma":"embrasser","lemmaPos":"verb","synonyms":["baiser","étreindre","adopter","épouser"],"number":"singular","pastTenses":"embrassée, a embrassé, a été embrassée","tense":"past","gender":"feminine","source":"embrassée"}