{"transcript":"ɑ̃ l‿ɔkyʁɑ̃s","exists":true,"definitions":["Dans le cas présent, dans cette situation particulière.","Au moment où cela se produit, le cas échéant."],"examples":["Il a fait une erreur, en l'occurrence une faute de calcul.","Si un problème survient, en l'occurrence une panne, contactez-nous.","La décision dépendra des faits, en l'occurrence de son témoignage."],"lemma":"en l'occurrence","lemmaPos":"adverb","synonyms":["dans ce cas","le cas échéant","précisément"],"number":"singular","source":"en l'occurrence"}