{"transcript":"ɛ̃teʀɛsəʀɛ","exists":true,"definitions":["Forme du verbe intéresser au conditionnel présent, troisième personne du singulier.","Manifester de l'intérêt pour quelque chose ou quelqu'un (hypothétiquement).","Attirer l'attention de quelqu'un (hypothétiquement)."],"examples":["Cela m'intéresserait beaucoup de savoir.","Qui cela intéresserait-il ?","Une telle proposition l'intéresserait sûrement."],"lemma":"intéresser","lemmaPos":"verb","synonyms":["captiver","passionner","concerner","attirer"],"number":"singular","pastTenses":"il a intéressé, il intéressa","tense":"present conditional","source":"intéresserait"}