{"transcript":"톝팪s톖lasj톖팪","exists":true,"definitions":["Exposition prolong칠e au soleil.","Maladie caus칠e par une exposition excessive au soleil, caract칠ris칠e par des maux de t칡te, de la fi칟vre, etc."],"examples":["Les insolations sont dangereuses.","Pr칠venir les insolations est crucial.","Les insolations peuvent 칡tre 칠vit칠es."],"lemma":"insolation","lemmaPos":"noun","synonyms":["coup de soleil","h칠liose"],"number":"plural","pluralForm":"les insolations","gender":"feminine","source":"insolations"}