{"transcript":"ɛ̃vɛstiʁ","exists":true,"definitions":["Placer des capitaux dans une entreprise, une affaire, etc., en vue d'en tirer un profit.","Consacrer son temps, son énergie, ses efforts à quelque chose.","Conférer un pouvoir, une dignité à quelqu'un.","Entourer une place forte pour l'attaquer."],"examples":["Il a décidé d'investir dans l'immobilier.","Elle s'investit pleinement dans son travail.","Le président a investi le nouveau ministre de ses fonctions.","Les troupes ont investi la ville."],"lemma":"investir","lemmaPos":"verb","synonyms":["placer","consacrer","conférer","assiéger"],"number":"singular","pastTenses":"il a investi, il est investi","tense":"present","source":"investir"}