{"transcript":"puʁɛ","exists":true,"definitions":["Troisième personne du singulier du conditionnel présent du verbe pouvoir.","Exprime une possibilité, une éventualité.","Suggère une hypothèse ou une supposition."],"examples":["Il pourrait pleuvoir demain.","Elle pourrait venir avec nous.","Cela pourrait être une bonne idée."],"lemma":"pouvoir","lemmaPos":"verb","synonyms":["pourrait","serait capable","aurait la possibilité"],"number":"singular","pastTenses":"a pu, a pu","tense":"present","source":"pourrait"}